LICENSE
README.md
setup.py
setuptools_dummy-0.1.0.4-py2.7.egg
django_postageapp_backend.egg-info/PKG-INFO
django_postageapp_backend.egg-info/SOURCES.txt
django_postageapp_backend.egg-info/dependency_links.txt
django_postageapp_backend.egg-info/requires.txt
django_postageapp_backend.egg-info/top_level.txt
postageapp/__init__.py
postageapp/backends.py