Metadata-Version: 1.1
Name: django-postageapp-backend
Version: 1.0.1
Summary: Postageapp email backend for Django framework
Home-page: UNKNOWN
Author: Fragaria, s.r.o.
Author-email: admin@fragaria.cz
License: GPLv2
Platform: UNKNOWN
Classifier: Development Status :: 4 - Beta
Classifier: Intended Audience :: Developers
Classifier: License :: OSI Approved :: BSD License
Classifier: Operating System :: OS Independent
Classifier: Framework :: Django
Classifier: Programming Language :: Python :: 2.7
Classifier: Operating System :: OS Independent
Classifier: Topic :: Internet :: WWW/HTTP :: Dynamic Content
Classifier: Topic :: Software Development :: Libraries :: Python Modules
